flowguard-0.1.3.dist-info/METADATA
flowguard-0.1.3.dist-info/WHEEL
flowguard-0.1.3.dist-info/licenses/LICENSE
flowguard/__init__.py
flowguard/__init__.pyi
flowguard/flowguard.abi3.so
flowguard/py.typed
flowguard-0.1.3.dist-info/RECORD
