Metadata-Version: 2.4
Name: flowguard
Version: 0.1.3
Classifier: Programming Language :: Rust
Classifier: Programming Language :: Python :: Implementation :: CPython
Classifier: Programming Language :: Python :: Implementation :: PyPy
Requires-Dist: typing-extensions==4.14.0 ; python_full_version < '3.10'
License-File: LICENSE
Summary: Rate limiting library for Python with sync/async support
Home-Page: https://github.com/Tapanhaz/flowguard
Author: Tapanhaz <tapanhaz@yahoo.com>
Author-email: Tapanhaz <tapanhaz@yahoo.com>
License: MIT
Requires-Python: >=3.8
Project-URL: Source Code, https://github.com/Tapanhaz/flowguard
